create_intro_cards.py
create_intro_cards-1.0.5.dist-info/LICENSE.txt
create_intro_cards-1.0.5.dist-info/METADATA
create_intro_cards-1.0.5.dist-info/WHEEL
create_intro_cards-1.0.5.dist-info/top_level.txt
create_intro_cards-1.0.5.dist-info/RECORD
