Metadata-Version: 2.2
Name: create-intro-cards
Version: 1.0.5
Summary: Convert a dataset of individuals' names, photos, and custom attributes into a PDF of “intro cards” that describe each individual.
Author: Bobby Math
License: BSD 3-Clause License
Project-URL: Homepage, https://www.github.com/robertfmath/create-intro-cards
Project-URL: Documentation, https://robertfmath.github.io/create-intro-cards
Keywords: introductions,intro,cards,matplotlib,pdf,visualization
Classifier: License :: OSI Approved :: BSD License
Classifier: Intended Audience :: Developers
Classifier: Programming Language :: Python :: 3.11
Classifier: Programming Language :: Python :: 3.12
Classifier: Programming Language :: Python :: 3.13
Classifier: Topic :: Software Development :: Libraries :: Python Modules
Classifier: Topic :: Multimedia :: Graphics
Requires-Python: >=3.11
License-File: LICENSE.txt
Requires-Dist: numpy>=1.26.1
Requires-Dist: pandas>=2.1.2
Requires-Dist: matplotlib>=3.8.1
Requires-Dist: Pillow>=10.1.0
Requires-Dist: ipykernel>=6.29.5
Provides-Extra: dev
Requires-Dist: ruff>=0.9.9; extra == "dev"
Requires-Dist: docformatter>=1.7.5; extra == "dev"
Requires-Dist: Sphinx>=7.2.6; extra == "dev"
Requires-Dist: pypdf>=5; extra == "dev"
Requires-Dist: typing_extensions>=4.6; extra == "dev"
